{
  "table": "Euro2016_1",
  "columns": [
    {
      "name": "Number of Records",
      "type": "smallint",
      "nullability": "NOT NULL"
    },
    {
      "name": "id",
      "type": "integer",
      "nullability": "NOT NULL"
    },
    {
      "name": "lang",
      "type": "varchar(3)",
      "nullability": "NOT NULL"
    },
    {
      "name": "latitude",
      "type": "varchar(12)",
      "nullability": "NULL"
    },
    {
      "name": "longitude",
      "type": "varchar(13)",
      "nullability": "NULL"
    },
    {
      "name": "polarity",
      "type": "varchar(8)",
      "nullability": "NULL"
    },
    {
      "name": "polarity_confidence",
      "type": "decimal(16, 15)",
      "nullability": "NULL"
    },
    {
      "name": "subjectivity",
      "type": "varchar(10)",
      "nullability": "NULL"
    },
    {
      "name": "subjectivity_confidence",
      "type": "decimal(16, 15)",
      "nullability": "NULL"
    },
    {
      "name": "tweet",
      "type": "varchar(402)",
      "nullability": "NOT NULL"
    },
    {
      "name": "tweeted_at",
      "type": "timestamp",
      "nullability": "NULL"
    }
  ]
}